struct_gpt-2.2.7.dist-info/METADATA
struct_gpt-2.2.7.dist-info/WHEEL
struct_gpt-2.2.7.dist-info/licenses/LICENSE
struct_gpt/__init__.py
struct_gpt/models.py
struct_gpt-2.2.7.dist-info/RECORD
