Metadata-Version: 2.1
Name: struct-gpt
Version: 2.2.7
Summary: structured llm outputs
Author-Email: Stephan Fitzpatrick <knowsuchagency@gmail.com>
License: MIT License
Project-URL: Source, https://github.com/knowsuchagency/struct-gpt
Requires-Python: >=3.10
Requires-Dist: openai>=0.27.6
Requires-Dist: pydantic>=1.10.7
Requires-Dist: ruamel-yaml>=0.17.24
